LICENSE
README.md
setup.py
docums_git_authors_plugin/__init__.py
docums_git_authors_plugin/ci.py
docums_git_authors_plugin/exclude.py
docums_git_authors_plugin/plugin.py
docums_git_authors_plugin/util.py
docums_git_authors_plugin.egg-info/PKG-INFO
docums_git_authors_plugin.egg-info/SOURCES.txt
docums_git_authors_plugin.egg-info/dependency_links.txt
docums_git_authors_plugin.egg-info/entry_points.txt
docums_git_authors_plugin.egg-info/requires.txt
docums_git_authors_plugin.egg-info/top_level.txt
docums_git_authors_plugin/git/__init__.py
docums_git_authors_plugin/git/author.py
docums_git_authors_plugin/git/command.py
docums_git_authors_plugin/git/commit.py
docums_git_authors_plugin/git/page.py
docums_git_authors_plugin/git/repo.py