Metadata-Version: 2.1
Name: docums-git-authors-plugin
Version: 1.0
Summary: docums plugin to display git authors of a page
Home-page: https://github.com/khanhduy1407/docums-git-authors-plugin
Author: NKDuy
Author-email: kn145660@gmail.com
License: MIT
Keywords: docums git contributors committers authors plugin
Platform: UNKNOWN
Classifier: Operating System :: OS Independent
Classifier: Programming Language :: Python
Classifier: Programming Language :: Python :: 3
Classifier: Programming Language :: Python :: 3.7
Classifier: Programming Language :: Python :: 3.8
Classifier: Programming Language :: Python :: 3.9
Classifier: Programming Language :: Python :: 3.10
Classifier: Programming Language :: Python :: 3 :: Only
Classifier: License :: OSI Approved :: MIT License
Classifier: Topic :: Documentation
Classifier: Topic :: Text Processing
Requires-Python: >=3.6
License-File: LICENSE
